{
  "kind": "collectionType",
  "collectionName": "messages",
  "info": {
    "singularName": "message",
    "pluralName": "messages",
    "displayName": "Message",
    "description": ""
  },
  "options": {
    "draftAndPublish": false
  },
  "pluginOptions": {},
  "attributes": {
    "name": {
      "type": "string",
      "required": true
    },
    "email": {
      "type": "string",
      "required": true
    },
    "phone": {
      "type": "string",
      "required": true
    },
    "subject": {
      "type": "string",
      "required": true
    },
    "message": {
      "type": "text",
      "required": true
    }
  }
}
